[{"id":0,"bd":1984,"dd":1997},{"id":1,"bd":1980,"dd":1980},{"id":2,"bd":1948,"dd":1993},{"id":3,"bd":1965,"dd":1971},{"id":4,"bd":1989,"dd":1991},{"id":5,"bd":1900,"dd":1914},{"id":6,"bd":1994,"dd":1994},{"id":7,"bd":1932,"dd":1985},{"id":8,"bd":1916,"dd":1992},{"id":9,"bd":1905,"dd":1935},{"id":10,"bd":1984,"dd":1991},{"id":11,"bd":1991,"dd":1997},{"id":12,"bd":1921,"dd":1973},{"id":13,"bd":1994,"dd":1996},{"id":14,"bd":1938,"dd":1938},{"id":15,"bd":1953,"dd":1974},{"id":16,"bd":1990,"dd":1997},{"id":17,"bd":1979,"dd":1985},{"id":18,"bd":1916,"dd":1982},{"id":19,"bd":1945,"dd":1986},{"id":20,"bd":1900,"dd":1972},{"id":21,"bd":1976,"dd":1988},{"id":22,"bd":1985,"dd":1991},{"id":23,"bd":1922,"dd":1983},{"id":24,"bd":1957,"dd":1958},{"id":25,"bd":1958,"dd":1963},{"id":26,"bd":1945,"dd":1963},{"id":27,"bd":1937,"dd":1976},{"id":28,"bd":1907,"dd":1946},{"id":29,"bd":1966,"dd":1979},{"id":30,"bd":1977,"dd":1990},{"id":31,"bd":1958,"dd":1983},{"id":32,"bd":1942,"dd":1955},{"id":33,"bd":1934,"dd":1983},{"id":34,"bd":1998,"dd":1998},{"id":35,"bd":1918,"dd":1948},{"id":36,"bd":1970,"dd":1973},{"id":37,"bd":1928,"dd":1961},{"id":38,"bd":1921,"dd":1942},{"id":39,"bd":1959,"dd":1994},{"id":40,"bd":1962,"dd":1996},{"id":41,"bd":1906,"dd":1919},{"id":42,"bd":1997,"dd":1997},{"id":43,"bd":1991,"dd":1998},{"id":44,"bd":1941,"dd":1965},{"id":45,"bd":1975,"dd":1993},{"id":46,"bd":1910,"dd":1973},{"id":47,"bd":1955,"dd":1971},{"id":48,"bd":1908,"dd":1990},{"id":49,"bd":1983,"dd":1989},{"id":50,"bd":1967,"dd":1995},{"id":51,"bd":1916,"dd":1989},{"id":52,"bd":1993,"dd":1995},{"id":53,"bd":1995,"dd":1998},{"id":54,"bd":1909,"dd":1960},{"id":55,"bd":1920,"dd":1982},{"id":56,"bd":1953,"dd":1962},{"id":57,"bd":1965,"dd":1982},{"id":58,"bd":1923,"dd":1942},{"id":59,"bd":1920,"dd":1961},{"id":60,"bd":1970,"dd":1992},{"id":61,"bd":1945,"dd":1998},{"id":62,"bd":1975,"dd":1991},{"id":63,"bd":1971,"dd":1971},{"id":64,"bd":1908,"dd":1957},{"id":65,"bd":1968,"dd":1992},{"id":66,"bd":1991,"dd":1991},{"id":67,"bd":1982,"dd":1983},{"id":68,"bd":1961,"dd":1976},{"id":69,"bd":1921,"dd":1961},{"id":70,"bd":1907,"dd":1991},{"id":71,"bd":1965,"dd":1980},{"id":72,"bd":1973,"dd":1992},{"id":73,"bd":1911,"dd":1957},{"id":74,"bd":1996,"dd":1996},{"id":75,"bd":1985,"dd":1995},{"id":76,"bd":1969,"dd":1978},{"id":77,"bd":1904,"dd":1929},{"id":78,"bd":1902,"dd":1997},{"id":79,"bd":1966,"dd":1979},{"id":80,"bd":1928,"dd":1982},{"id":81,"bd":1947,"dd":1969},{"id":82,"bd":1910,"dd":1933},{"id":83,"bd":1901,"dd":1946},{"id":84,"bd":1979,"dd":1991},{"id":85,"bd":1925,"dd":1989},{"id":86,"bd":1910,"dd":1955},{"id":87,"bd":1955,"dd":1977},{"id":88,"bd":1978,"dd":1992},{"id":89,"bd":1981,"dd":1998},{"id":90,"bd":1953,"dd":1978},{"id":91,"bd":1956,"dd":1990},{"id":92,"bd":1984,"dd":1987},{"id":93,"bd":1921,"dd":1993},{"id":94,"bd":1987,"dd":1995},{"id":95,"bd":1954,"dd":1997},{"id":96,"bd":1949,"dd":1951},{"id":97,"bd":1945,"dd":1965},{"id":98,"bd":1909,"dd":1974},{"id":99,"bd":1972,"dd":1993},{"id":100,"bd":1943,"dd":1978},{"id":101,"bd":1905,"dd":1936},{"id":102,"bd":1917,"dd":1975},{"id":103,"bd":1966,"dd":1967},{"id":104,"bd":1950,"dd":1987},{"id":105,"bd":1976,"dd":1996},{"id":106,"bd":1972,"dd":1974},{"id":107,"bd":1985,"dd":1985},{"id":108,"bd":1962,"dd":1976},{"id":109,"bd":1968,"dd":1974},{"id":110,"bd":1971,"dd":1982},{"id":111,"bd":1996,"dd":1996},{"id":112,"bd":1930,"dd":1998},{"id":113,"bd":1967,"dd":1977},{"id":114,"bd":1919,"dd":1986},{"id":115,"bd":1954,"dd":1984},{"id":116,"bd":1982,"dd":1984},{"id":117,"bd":1912,"dd":1961},{"id":118,"bd":1968,"dd":1978},{"id":119,"bd":1977,"dd":1977},{"id":120,"bd":1918,"dd":1931},{"id":121,"bd":1923,"dd":1961},{"id":122,"bd":1952,"dd":1959},{"id":123,"bd":1998,"dd":1998},{"id":124,"bd":1972,"dd":1980},{"id":125,"bd":1933,"dd":1975},{"id":126,"bd":1934,"dd":1934},{"id":127,"bd":1940,"dd":1978},{"id":128,"bd":1989,"dd":1997},{"id":129,"bd":1986,"dd":1996},{"id":130,"bd":1936,"dd":1986},{"id":131,"bd":1909,"dd":1998},{"id":132,"bd":1934,"dd":1964},{"id":133,"bd":1914,"dd":1958},{"id":134,"bd":1972,"dd":1998},{"id":135,"bd":1972,"dd":1987},{"id":136,"bd":1947,"dd":1963},{"id":137,"bd":1982,"dd":1998},{"id":138,"bd":1996,"dd":1998},{"id":139,"bd":1955,"dd":1978},{"id":140,"bd":1907,"dd":1938},{"id":141,"bd":1909,"dd":1989},{"id":142,"bd":1966,"dd":1995},{"id":143,"bd":1959,"dd":1976},{"id":144,"bd":1994,"dd":1994},{"id":145,"bd":1947,"dd":1954},{"id":146,"bd":1952,"dd":1963},{"id":147,"bd":1923,"dd":1998},{"id":148,"bd":1950,"dd":1961},{"id":149,"bd":1974,"dd":1983},{"id":150,"bd":1998,"dd":1998},{"id":151,"bd":1908,"dd":1955},{"id":152,"bd":1968,"dd":1978},{"id":153,"bd":1922,"dd":1974},{"id":154,"bd":1973,"dd":1990},{"id":155,"bd":1909,"dd":1981},{"id":156,"bd":1909,"dd":1995},{"id":157,"bd":1915,"dd":1920},{"id":158,"bd":1977,"dd":1990},{"id":159,"bd":1940,"dd":1996},{"id":160,"bd":1974,"dd":1978},{"id":161,"bd":1926,"dd":1972},{"id":162,"bd":1987,"dd":1995},{"id":163,"bd":1980,"dd":1998},{"id":164,"bd":1919,"dd":1928},{"id":165,"bd":1955,"dd":1996},{"id":166,"bd":1936,"dd":1955},{"id":167,"bd":1996,"dd":1997},{"id":168,"bd":1954,"dd":1998},{"id":169,"bd":1919,"dd":1985},{"id":170,"bd":1944,"dd":1960},{"id":171,"bd":1972,"dd":1975},{"id":172,"bd":1979,"dd":1993},{"id":173,"bd":1955,"dd":1997},{"id":174,"bd":1937,"dd":1997},{"id":175,"bd":1902,"dd":1903},{"id":176,"bd":1916,"dd":1990},{"id":177,"bd":1945,"dd":1979},{"id":178,"bd":1976,"dd":1993},{"id":179,"bd":1924,"dd":1927},{"id":180,"bd":1921,"dd":1992},{"id":181,"bd":1944,"dd":1983},{"id":182,"bd":1951,"dd":1992},{"id":183,"bd":1962,"dd":1963},{"id":184,"bd":1963,"dd":1965},{"id":185,"bd":1986,"dd":1991},{"id":186,"bd":1926,"dd":1972},{"id":187,"bd":1956,"dd":1979},{"id":188,"bd":1907,"dd":1976},{"id":189,"bd":1922,"dd":1923},{"id":190,"bd":1979,"dd":1991},{"id":191,"bd":1928,"dd":1943},{"id":192,"bd":1971,"dd":1978},{"id":193,"bd":1938,"dd":1943},{"id":194,"bd":1989,"dd":1997},{"id":195,"bd":1908,"dd":1982},{"id":196,"bd":1993,"dd":1998},{"id":197,"bd":1900,"dd":1920},{"id":198,"bd":1953,"dd":1982},{"id":199,"bd":1916,"dd":1945},{"id":200,"bd":1907,"dd":1967}]